odoo/addons/stock_picking_default_planned_transfer/README.rst
odoo/addons/stock_picking_default_planned_transfer/__init__.py
odoo/addons/stock_picking_default_planned_transfer/__manifest__.py
odoo/addons/stock_picking_default_planned_transfer/hooks.py
odoo/addons/stock_picking_default_planned_transfer/i18n/stock_picking_default_planned_transfer.pot
odoo/addons/stock_picking_default_planned_transfer/readme/CONTRIBUTORS.rst
odoo/addons/stock_picking_default_planned_transfer/readme/DESCRIPTION.rst
odoo/addons/stock_picking_default_planned_transfer/static/description/icon.png
odoo/addons/stock_picking_default_planned_transfer/static/description/index.html
odoo14_addon_stock_picking_default_planned_transfer-14.0.1.0.1.dist-info/METADATA
odoo14_addon_stock_picking_default_planned_transfer-14.0.1.0.1.dist-info/WHEEL
odoo14_addon_stock_picking_default_planned_transfer-14.0.1.0.1.dist-info/top_level.txt
odoo14_addon_stock_picking_default_planned_transfer-14.0.1.0.1.dist-info/RECORD
